wg_helper_script/__init__.py
wg_helper_script/__main__.py
wg_helper_script/cli.py
wg_helper_script/common.py
wg_helper_script/config.py
wg_helper_script/commands/__init__.py
wg_helper_script/commands/client_add_cmd.py
wg_helper_script/commands/client_disable_cmd.py
wg_helper_script/commands/client_remove_cmd.py
wg_helper_script/commands/emit_configs_cmd.py
wg_helper_script/commands/init_cmd.py
wg_helper_script/commands/validate_cfg_cmd.py
wg_helper_script-0.1.0.dist-info/licenses/LICENSE
wg_helper_script-0.1.0.dist-info/METADATA
wg_helper_script-0.1.0.dist-info/WHEEL
wg_helper_script-0.1.0.dist-info/entry_points.txt
wg_helper_script-0.1.0.dist-info/top_level.txt
wg_helper_script-0.1.0.dist-info/RECORD
