Metadata-Version: 2.4
Name: wg-helper-script
Version: 0.1.0
Summary: WireGuard helper CLI (configs, clients, QR)
Author: Contributors
License-Expression: MIT
Project-URL: Homepage, https://github.com/xobotyi/wg-helper-script
Project-URL: Repository, https://github.com/xobotyi/wg-helper-script
Project-URL: Issues, https://github.com/xobotyi/wg-helper-script/issues
Classifier: Programming Language :: Python :: 3
Classifier: Programming Language :: Python :: 3 :: Only
Classifier: Programming Language :: Python :: 3.11
Classifier: Programming Language :: Python :: 3.12
Classifier: Operating System :: OS Independent
Requires-Python: >=3.11
License-File: LICENSE
Requires-Dist: pyyaml>=6
Requires-Dist: cryptography>=41
Requires-Dist: qrcode[pil]>=7
Provides-Extra: dev
Requires-Dist: pytest>=8; extra == "dev"
Requires-Dist: ruff>=0.5; extra == "dev"
Requires-Dist: mypy>=1.10; extra == "dev"
Dynamic: license-file
